blockrun_llm_xrpl/__init__.py
blockrun_llm_xrpl/client.py
blockrun_llm_xrpl/types.py
blockrun_llm_xrpl/wallet.py
blockrun_llm_xrpl-0.1.0.dist-info/METADATA
blockrun_llm_xrpl-0.1.0.dist-info/WHEEL
blockrun_llm_xrpl-0.1.0.dist-info/RECORD
