Metadata-Version: 2.4
Name: blockrun-llm-xrpl
Version: 0.1.0
Summary: BlockRun SDK for XRPL - Pay-per-request AI via x402 with RLUSD
Project-URL: Homepage, https://blockrun.ai
Project-URL: Documentation, https://docs.blockrun.ai
Project-URL: Repository, https://github.com/BlockRunAI/blockrun-llm-xrpl
Author-email: BlockRun <hello@blockrun.ai>
License-Expression: MIT
Keywords: ai,claude,gemini,llm,micropayments,openai,rlusd,x402,xrpl
Classifier: Development Status :: 4 - Beta
Classifier: Intended Audience :: Developers
Classifier: License :: OSI Approved :: MIT License
Classifier: Programming Language :: Python :: 3
Classifier: Programming Language :: Python :: 3.9
Classifier: Programming Language :: Python :: 3.10
Classifier: Programming Language :: Python :: 3.11
Classifier: Programming Language :: Python :: 3.12
Classifier: Topic :: Scientific/Engineering :: Artificial Intelligence
Requires-Python: >=3.9
Requires-Dist: httpx>=0.25.0
Requires-Dist: pydantic>=2.0.0
Requires-Dist: x402-xrpl>=0.1.0
Requires-Dist: xrpl-py>=4.0.0
Provides-Extra: dev
Requires-Dist: black>=24.0.0; extra == 'dev'
Requires-Dist: mypy>=1.0.0; extra == 'dev'
Requires-Dist: pytest-asyncio>=0.21.0; extra == 'dev'
Requires-Dist: pytest>=7.0.0; extra == 'dev'
Requires-Dist: ruff>=0.1.0; extra == 'dev'
